chevrons/__init__.py
chevrons/tests.py
chevrons/text.py
chevrons_re-0.0.1.dist-info/LICENSE
chevrons_re-0.0.1.dist-info/METADATA
chevrons_re-0.0.1.dist-info/WHEEL
chevrons_re-0.0.1.dist-info/top_level.txt
chevrons_re-0.0.1.dist-info/RECORD
