Metadata-Version: 2.1
Name: chevrons-re
Version: 0.0.1
Summary: Chevrons for quotes
Home-page: https://github.com/Ian-Gabaraev/chevrons
Author: Ian Gabaraev
Author-email: hrattisianees@gmail.com
License: UNKNOWN
Platform: UNKNOWN
Classifier: Programming Language :: Python :: 3
Classifier: License :: OSI Approved :: MIT License
Classifier: Operating System :: OS Independent
Requires-Python: >=3.6
